docling_litellm_picture_description/__init__.py
docling_litellm_picture_description/picture_description_litellm_model.py
docling_litellm_picture_description/datamodel/pipeline_options.py
docling_litellm_picture_description/plugins/__init__.py
docling_litellm_picture_description/plugins/docling_litellm_picture_description.py
docling_litellm_picture_description-0.1.1.dist-info/licenses/LICENSE
docling_litellm_picture_description-0.1.1.dist-info/METADATA
docling_litellm_picture_description-0.1.1.dist-info/WHEEL
docling_litellm_picture_description-0.1.1.dist-info/entry_points.txt
docling_litellm_picture_description-0.1.1.dist-info/top_level.txt
docling_litellm_picture_description-0.1.1.dist-info/RECORD
