Metadata-Version: 2.4
Name: docling-litellm-picture-description
Version: 0.1.1
Summary: Docling plugin for LiteLLM picture description
Requires-Python: >=3.11
License-File: LICENSE
Requires-Dist: docling>=2.39.0
Requires-Dist: litellm>=1.72.0
Dynamic: license-file
